README.md
cli/__init__.py
cli/main.py
cli/commands/__init__.py
cli/commands/scan.py
cli/commands/test.py
githubparsers/__init__.py
githubparsers/workflowparser.py
githubparsers/models/job.py
githubparsers/models/step.py
githubparsers/models/workflow.py
httpclients/__init__.py
httpclients/base_httpclient.py
httpclients/nvd_httpclient.py
httpclients/responsemodels/cves_response.py
models/__init__.py
models/cve.py
models/cvss.py
utils/__init__.py
utils/log_utils.py
ci_cerberus-0.1.7.dist-info/METADATA
ci_cerberus-0.1.7.dist-info/WHEEL
ci_cerberus-0.1.7.dist-info/entry_points.txt
ci_cerberus-0.1.7.dist-info/RECORD
